twootfeed/__init__.py
twootfeed/__main__.py
twootfeed/config.example.yml
twootfeed/config.py
twootfeed/mastodon/__init__.py
twootfeed/mastodon/generate_toots_feed.py
twootfeed/mastodon/get_api.py
twootfeed/mastodon/routes.py
twootfeed/twitter/__init__.py
twootfeed/twitter/generate_tweets_feed.py
twootfeed/twitter/get_api.py
twootfeed/twitter/routes.py
twootfeed/utils/__init__.py
twootfeed/utils/config.py
twootfeed/utils/create_mastodon_client.py
twootfeed/utils/decorator.py
twootfeed/utils/exceptions.py
twootfeed/utils/feed_generation.py
twootfeed-0.7.4.dist-info/LICENCE
twootfeed-0.7.4.dist-info/METADATA
twootfeed-0.7.4.dist-info/WHEEL
twootfeed-0.7.4.dist-info/entry_points.txt
twootfeed-0.7.4.dist-info/top_level.txt
twootfeed-0.7.4.dist-info/RECORD
