Metadata-Version: 2.1
Name: twootfeed
Version: 0.7.4
Summary: generate a rss feed from Twitter or Mastodon search
Home-page: https://github.com/SamR1/python-twootfeed
Author: SamR1
License: The MIT License (MIT)
Project-URL: Documentation, https://samr1.github.io/python-twootfeed
Keywords: rss,twitter,mastodon,search
Platform: linux
Classifier: Development Status :: 4 - Beta
Classifier: Framework :: Flask
Classifier: Intended Audience :: Developers
Classifier: License :: OSI Approved :: MIT License
Classifier: Operating System :: POSIX :: Linux
Classifier: Programming Language :: Python :: 3
Classifier: Programming Language :: Python :: 3.8
Classifier: Programming Language :: Python :: 3.9
Classifier: Programming Language :: Python :: 3.10
Classifier: Programming Language :: Python :: 3.11
Classifier: Programming Language :: Python :: 3.12
Classifier: Topic :: Internet :: WWW/HTTP
Requires-Python: >=3.8.1
License-File: LICENCE
Requires-Dist: beautifulsoup4 ==4.12.2
Requires-Dist: feedgenerator ==2.1.0
Requires-Dist: Flask ==3.0.0
Requires-Dist: gunicorn ==21.2.0
Requires-Dist: Mastodon.py ==1.8.1
Requires-Dist: pytz ==2023.3.post1
Requires-Dist: PyYAML ==6.0.1
Requires-Dist: tweepy ==4.14.0
Provides-Extra: doc
Requires-Dist: sphinx ; extra == 'doc'
Requires-Dist: sphinx-rtd-theme ; extra == 'doc'
Requires-Dist: recommonmark ; extra == 'doc'
Provides-Extra: test
Requires-Dist: flake8 ; extra == 'test'
Requires-Dist: mypy ; extra == 'test'
Requires-Dist: pytest-cov ; extra == 'test'
Requires-Dist: pytest-isort ; extra == 'test'
Requires-Dist: pytest-black ; extra == 'test'
Requires-Dist: types-pytz ; extra == 'test'
Requires-Dist: types-PyYAML ; extra == 'test'
